<annotation>
	<folder>JPEGImages</folder>
	<filename>012.jpg</filename>
	<path>/Users/donghongda/Python/课堂笔记/deep_learn/self_expand/csdn_course/yolov3/项目文件/darknet/VOCdevkit/VOC2007/JPEGImages/012.jpg</path>
	<source>
		<database>Unknown</database>
	</source>
	<size>
		<width>500</width>
		<height>500</height>
		<depth>3</depth>
	</size>
	<segmented>0</segmented>
	<object>
		<name>keyboard</name>
		<pose>Unspecified</pose>
		<truncated>0</truncated>
		<difficult>0</difficult>
		<bndbox>
			<xmin>4</xmin>
			<ymin>84</ymin>
			<xmax>443</xmax>
			<ymax>408</ymax>
		</bndbox>
	</object>
	<object>
		<name>mouse</name>
		<pose>Unspecified</pose>
		<truncated>0</truncated>
		<difficult>0</difficult>
		<bndbox>
			<xmin>356</xmin>
			<ymin>167</ymin>
			<xmax>495</xmax>
			<ymax>438</ymax>
		</bndbox>
	</object>
</annotation>
